ocr_pdf2txt/__init__.py
ocr_pdf2txt/core.py
ocr_pdf2txt-0.1.2.dist-info/METADATA
ocr_pdf2txt-0.1.2.dist-info/WHEEL
ocr_pdf2txt-0.1.2.dist-info/top_level.txt
ocr_pdf2txt-0.1.2.dist-info/RECORD
