Metadata-Version: 2.2
Name: ocr_pdf2txt
Version: 0.1.2
Summary: OCR library with advanced PDF to text, layout visualization, audio generation, table extraction, summarization, and translation
Home-page: https://github.com/VerisimilitudeX/ocr_pdf2txt
Author: Piyush Acharya
Author-email: junk@piyushacharya.com
Classifier: Programming Language :: Python :: 3
Classifier: License :: OSI Approved :: MIT License
Classifier: Operating System :: OS Independent
Requires-Python: >=3.7
Requires-Dist: pytesseract
Requires-Dist: pdf2image
Requires-Dist: spacy
Requires-Dist: nltk
Requires-Dist: Pillow
Requires-Dist: gTTS
Requires-Dist: tabula-py
Requires-Dist: transformers
Requires-Dist: googletrans==4.0.0-rc1
Requires-Dist: torch
Dynamic: author
Dynamic: author-email
Dynamic: classifier
Dynamic: description
Dynamic: description-content-type
Dynamic: home-page
Dynamic: requires-dist
Dynamic: requires-python
Dynamic: summary
